{
  "version": "1.0.0",
  "chainId": "31337",
  "createdAt": 1700552415329,
  "meta": {
    "name": "Generated by multisig.ts"
  },
  "transactions": [
    {
      "to": "0x6521a549834F5E6d253CD2e5F4fbe4048f86cd7b",
      "value": "0",
      "contractMethod": {
        "inputs": [
          {
            "internalType": "address",
            "name": "_lpToken",
            "type": "address"
          },
          {
            "internalType": "address",
            "name": "_boostedRewarder",
            "type": "address"
          }
        ],
        "name": "add(address,address)",
        "payable": false
      },
      "contractInputsValues": {
        "_lpToken": "0xe07829c8B7F934e03C83B0dC1fd2cCC9b62036D8",
        "_boostedRewarder": "0x0000000000000000000000000000000000000000"
      }
    },
    {
      "to": "0x6521a549834F5E6d253CD2e5F4fbe4048f86cd7b",
      "value": "0",
      "contractMethod": {
        "inputs": [
          {
            "internalType": "address",
            "name": "_lpToken",
            "type": "address"
          },
          {
            "internalType": "address",
            "name": "_boostedRewarder",
            "type": "address"
          }
        ],
        "name": "add(address,address)",
        "payable": false
      },
      "contractInputsValues": {
        "_lpToken": "0xE2a60C52C4abB9fbc3f711da3cb9E633269DBC67",
        "_boostedRewarder": "0x0000000000000000000000000000000000000000"
      }
    },
    {
      "to": "0x640e7Ecd9346AA7190EFeb47Be24742086f78F47",
      "value": "0",
      "contractMethod": {
        "inputs": [
          {
            "internalType": "address",
            "name": "_token",
            "type": "address"
          }
        ],
        "name": "whitelistRewardToken(address)",
        "payable": false
      },
      "contractInputsValues": {
        "_token": "0xE5393cdBC4Fe7B62F1d76A990Ca7Da17ad718313"
      }
    },
    {
      "to": "0x640e7Ecd9346AA7190EFeb47Be24742086f78F47",
      "value": "0",
      "contractMethod": {
        "inputs": [
          {
            "internalType": "address",
            "name": "_token",
            "type": "address"
          },
          {
            "internalType": "address",
            "name": "_deployer",
            "type": "address"
          }
        ],
        "name": "setRewarderDeployer(address,address)",
        "payable": false
      },
      "contractInputsValues": {
        "_token": "0xe07829c8B7F934e03C83B0dC1fd2cCC9b62036D8",
        "_deployer": "0xF6EC90f57D4042c61935882c0DA67D6A3a886F98"
      }
    },
    {
      "to": "0x640e7Ecd9346AA7190EFeb47Be24742086f78F47",
      "value": "0",
      "contractMethod": {
        "inputs": [
          {
            "internalType": "address",
            "name": "_token",
            "type": "address"
          },
          {
            "internalType": "address",
            "name": "_deployer",
            "type": "address"
          }
        ],
        "name": "setRewarderDeployer(address,address)",
        "payable": false
      },
      "contractInputsValues": {
        "_token": "0xE2a60C52C4abB9fbc3f711da3cb9E633269DBC67",
        "_deployer": "0xF6EC90f57D4042c61935882c0DA67D6A3a886F98"
      }
    },
    {
      "to": "0x640e7Ecd9346AA7190EFeb47Be24742086f78F47",
      "value": "0",
      "contractMethod": {
        "inputs": [
          {
            "internalType": "address",
            "name": "_lpToken",
            "type": "address"
          },
          {
            "internalType": "uint256",
            "name": "_startTimestamp",
            "type": "uint256"
          },
          {
            "internalType": "address",
            "name": "_rewardToken",
            "type": "address"
          },
          {
            "internalType": "uint96",
            "name": "_tokenPerSec",
            "type": "uint96"
          }
        ],
        "name": "deployRewarderContractAndSetRewarder(address,uint256,address,uint96)",
        "payable": false
      },
      "contractInputsValues": {
        "_lpToken": "0xe07829c8B7F934e03C83B0dC1fd2cCC9b62036D8",
        "_startTimestamp": "1700632500",
        "_rewardToken": "0xE5393cdBC4Fe7B62F1d76A990Ca7Da17ad718313",
        "_tokenPerSec": "192901234567901234"
      }
    },
    {
      "to": "0x640e7Ecd9346AA7190EFeb47Be24742086f78F47",
      "value": "0",
      "contractMethod": {
        "inputs": [
          {
            "internalType": "address",
            "name": "_lpToken",
            "type": "address"
          },
          {
            "internalType": "uint256",
            "name": "_startTimestamp",
            "type": "uint256"
          },
          {
            "internalType": "address",
            "name": "_rewardToken",
            "type": "address"
          },
          {
            "internalType": "uint96",
            "name": "_tokenPerSec",
            "type": "uint96"
          }
        ],
        "name": "deployRewarderContractAndSetRewarder(address,uint256,address,uint96)",
        "payable": false
      },
      "contractInputsValues": {
        "_lpToken": "0xE2a60C52C4abB9fbc3f711da3cb9E633269DBC67",
        "_startTimestamp": "1700632500",
        "_rewardToken": "0xE5393cdBC4Fe7B62F1d76A990Ca7Da17ad718313",
        "_tokenPerSec": "192901234567901234"
      }
    },
    {
      "to": "0x640e7Ecd9346AA7190EFeb47Be24742086f78F47",
      "value": "0",
      "contractMethod": {
        "inputs": [
          {
            "internalType": "address",
            "name": "_token",
            "type": "address"
          },
          {
            "internalType": "address",
            "name": "_deployer",
            "type": "address"
          }
        ],
        "name": "setRewarderDeployer(address,address)",
        "payable": false
      },
      "contractInputsValues": {
        "_token": "0xe07829c8B7F934e03C83B0dC1fd2cCC9b62036D8",
        "_deployer": "0x3d7C9f013443abc3cCa17e00ED294B77A6dd9F96"
      }
    },
    {
      "to": "0x640e7Ecd9346AA7190EFeb47Be24742086f78F47",
      "value": "0",
      "contractMethod": {
        "inputs": [
          {
            "internalType": "address",
            "name": "_token",
            "type": "address"
          },
          {
            "internalType": "address",
            "name": "_deployer",
            "type": "address"
          }
        ],
        "name": "setRewarderDeployer(address,address)",
        "payable": false
      },
      "contractInputsValues": {
        "_token": "0xE2a60C52C4abB9fbc3f711da3cb9E633269DBC67",
        "_deployer": "0x3d7C9f013443abc3cCa17e00ED294B77A6dd9F96"
      }
    }
  ]
}
