{
  "version": "1.0.0",
  "chainId": "1",
  "createdAt": 1695795748893,
  "meta": {
    "name": "Generated by multisig.ts"
  },
  "transactions": [
    {
      "to": "0xCd69ca1e4dA21F65896A8d2e4ea625FF5B19E8Fe",
      "value": "0",
      "contractMethod": {
        "inputs": [
          {
            "internalType": "address",
            "name": "_token",
            "type": "address"
          },
          {
            "internalType": "address",
            "name": "_deployer",
            "type": "address"
          }
        ],
        "name": "setBribeDeployer(address,address)",
        "payable": false
      },
      "contractInputsValues": {
        "_token": "0x724515010904518eCF638Cc6d693046B82548068",
        "_deployer": "0x6e74053a3798e0fC9a9775F7995316b27f21c4D2"
      }
    },
    {
      "to": "0xCd69ca1e4dA21F65896A8d2e4ea625FF5B19E8Fe",
      "value": "0",
      "contractMethod": {
        "inputs": [
          {
            "internalType": "address",
            "name": "_token",
            "type": "address"
          },
          {
            "internalType": "address",
            "name": "_deployer",
            "type": "address"
          }
        ],
        "name": "setBribeDeployer(address,address)",
        "payable": false
      },
      "contractInputsValues": {
        "_token": "0x51E073D92b0c226F7B0065909440b18A85769606",
        "_deployer": "0x6e74053a3798e0fC9a9775F7995316b27f21c4D2"
      }
    },
    {
      "to": "0xCd69ca1e4dA21F65896A8d2e4ea625FF5B19E8Fe",
      "value": "0",
      "contractMethod": {
        "inputs": [
          {
            "internalType": "address",
            "name": "_token",
            "type": "address"
          },
          {
            "internalType": "address",
            "name": "_deployer",
            "type": "address"
          }
        ],
        "name": "setBribeDeployer(address,address)",
        "payable": false
      },
      "contractInputsValues": {
        "_token": "0xC096FF2606152eD2A06dd12F15A3c0466Aa5A9fa",
        "_deployer": "0x6e74053a3798e0fC9a9775F7995316b27f21c4D2"
      }
    },
    {
      "to": "0xCd69ca1e4dA21F65896A8d2e4ea625FF5B19E8Fe",
      "value": "0",
      "contractMethod": {
        "inputs": [
          {
            "internalType": "address",
            "name": "_token",
            "type": "address"
          },
          {
            "internalType": "address",
            "name": "_deployer",
            "type": "address"
          }
        ],
        "name": "setBribeDeployer(address,address)",
        "payable": false
      },
      "contractInputsValues": {
        "_token": "0x25C9dd8a3774EF7C918cd28ff59cF9e29504C914",
        "_deployer": "0x68258012DA3B933a81617FD08c9382a60B87cA98"
      }
    },
    {
      "to": "0xCd69ca1e4dA21F65896A8d2e4ea625FF5B19E8Fe",
      "value": "0",
      "contractMethod": {
        "inputs": [
          {
            "internalType": "address",
            "name": "_token",
            "type": "address"
          },
          {
            "internalType": "address",
            "name": "_deployer",
            "type": "address"
          }
        ],
        "name": "setBribeDeployer(address,address)",
        "payable": false
      },
      "contractInputsValues": {
        "_token": "0x75Eaa804518a66196946598317Aed57Ef86235Fe",
        "_deployer": "0x68258012DA3B933a81617FD08c9382a60B87cA98"
      }
    }
  ]
}
